humata/__init__.py
humata-0.1.5.dist-info/LICENSE
humata-0.1.5.dist-info/METADATA
humata-0.1.5.dist-info/WHEEL
humata-0.1.5.dist-info/top_level.txt
humata-0.1.5.dist-info/RECORD
