Metadata-Version: 2.1
Name: humata
Version: 0.1.5
Summary: Humata.ai Python SDK
Home-page: https://www.humata.ai/
Author: Humata
Author-email: support@humata.ai
Project-URL: Documentation, https://www.humata.ai/
Project-URL: Bug Reports, https://ww.humata.ai/
Keywords: humata,humata.ai
Requires-Python: >=3.6
License-File: LICENSE
Requires-Dist: supabase ==2.3.1
Provides-Extra: dev
Requires-Dist: check-manifest ; extra == 'dev'
